browsergym/assistantbench/__init__.py
browsergym/assistantbench/task.py
browsergym/assistantbench/utils.py
browsergym/assistantbench/evaluation/evaluator.py
browsergym/assistantbench/evaluation/evaluate_utils/evaluate_dicts.py
browsergym/assistantbench/evaluation/evaluate_utils/evaluate_factory.py
browsergym/assistantbench/evaluation/evaluate_utils/evaluate_numbers.py
browsergym/assistantbench/evaluation/evaluate_utils/evaluate_strings.py
browsergym/assistantbench/evaluation/evaluate_utils/utils.py
browsergym_assistantbench-0.14.3.dist-info/METADATA
browsergym_assistantbench-0.14.3.dist-info/WHEEL
browsergym_assistantbench-0.14.3.dist-info/RECORD
